qstion/__init__.py
qstion/_exc.py
qstion/_qs_core.py
qstion/_struct_core.py
qstion/parser.py
qstion/stringifier.py
qstion-1.1.7.dist-info/LICENSE
qstion-1.1.7.dist-info/METADATA
qstion-1.1.7.dist-info/WHEEL
qstion-1.1.7.dist-info/top_level.txt
qstion-1.1.7.dist-info/RECORD
