Metadata-Version: 2.1
Name: qstion
Version: 1.1.7
Summary: Simple package for parsing querystrings into nested dictionaries and vice versa.
Author-email: Marek Nemeth <99m.nemeth@gmail.com>
License: BSD-3-Clause
Project-URL: Homepage, https://github.com/kajotgames/qstion
Project-URL: Bug Tracker, https://github.com/kajotgames/qstion/issues
Project-URL: Documentation, https://github.com/kajotgames/qstion/blob/main/README.md
Keywords: querystring,query,string,url,parse,serialize,deserialize,nested,dict,dictionary,qs,qstion
Classifier: License :: OSI Approved :: BSD License
Classifier: Operating System :: OS Independent
Classifier: Development Status :: 5 - Production/Stable
Classifier: Intended Audience :: Developers
Classifier: Programming Language :: Python :: 3
Classifier: Typing :: Typed
Requires-Python: >=3.11
License-File: LICENSE
